kantex/__init__.py
kantex/_document.py
kantex/_items.py
kantex/_sections.py
kantex/_styles.py
kantex/_base/__init__.py
kantex/_base/document.py
kantex/_base/items.py
kantex/_base/sections.py
kantex/_base/styles.py
kantex/html/__init__.py
kantex/html/_document.py
kantex/html/_items.py
kantex/html/_sections.py
kantex/html/_styles.py
kantex/md/__init__.py
kantex/md/_document.py
kantex/md/_items.py
kantex/md/_sections.py
kantex/md/_styles.py
kantex-0.2.0.dist-info/LICENSE
kantex-0.2.0.dist-info/METADATA
kantex-0.2.0.dist-info/WHEEL
kantex-0.2.0.dist-info/top_level.txt
kantex-0.2.0.dist-info/RECORD
