Metadata-Version: 2.1
Name: kantex
Version: 0.2.0
Summary: Layout text automatically using classes
Home-page: https://github.com/kantek/KanTeX
Author: Simon Schürrle
Author-email: simon@kv2.dev
License: License :: OSI Approved :: GNU Lesser General Public License v3 (LGPLv3)
Platform: UNKNOWN
Classifier: Development Status :: 5 - Production/Stable
Classifier: Programming Language :: Python :: 3.6
Classifier: Programming Language :: Python :: 3.7
Classifier: Programming Language :: Python :: Implementation :: CPython
Classifier: Typing :: Typed
Requires-Python: >=3.6
